apparition/__init__.py
apparition/__main__.py
apparition/apparate.py
apparition/exceptions.py
apparition/io.py
apparition/main.py
apparition/resources/apparate.sh
apparition/utils.py
apparition-0.1.0.dist-info/METADATA
apparition-0.1.0.dist-info/LICENSE
apparition-0.1.0.dist-info/WHEEL
apparition-0.1.0.dist-info/entry_points.txt
apparition-0.1.0.dist-info/RECORD
