Metadata-Version: 2.1
Name: apparition
Version: 0.1.0
Summary: Apparate through your file system.
License: MIT
Author: David Härer
Author-email: david@95co.de
Requires-Python: >=3.10,<4.0
Classifier: License :: OSI Approved :: MIT License
Classifier: Programming Language :: Python :: 3
Classifier: Programming Language :: Python :: 3.10
Classifier: Programming Language :: Python :: 3.11
Requires-Dist: appdirs (>=1.4.4,<2.0.0)
Requires-Dist: pyyaml (>=6.0,<7.0)
Requires-Dist: rich (>=13.3.1,<14.0.0)
Requires-Dist: sh (>=1.14.3,<2.0.0)
Requires-Dist: typer (>=0.7.0,<0.8.0)
